{
	"$schema": "../../schemas/code-crispies-module-schema.json",
	"id": "welcome",
	"title": "Willkommen",
	"description": "Erste Schritte mit Code Crispies",
	"mode": "html",
	"difficulty": "beginner",
	"excludeFromProgress": true,
	"lessons": [
		{
			"id": "hello",
			"title": "Hallo!",
			"description": "<strong>Willkommen bei Code Crispies!</strong> Lerne CSS und HTML durch praktische Übungen.<br><br><strong>So funktioniert's:</strong><br>1. Lies die Aufgabe links<br>2. Schreibe Code im Editor<br>3. Sieh Live-Ergebnisse in der Vorschau<br><br><strong>Tipps:</strong> Nutze <kbd>Strg+Z</kbd> zum Rückgängigmachen. Öffne das Menü (☰) um alle Module zu erkunden.",
			"task": "Schreibe <code>Hello World</code> zum Starten",
			"previewHTML": "",
			"previewBaseCSS": "body { font-family: system-ui, sans-serif; padding: 20px; text-align: center; font-size: 2rem; color: #6366f1; font-weight: bold; }",
			"sandboxCSS": "",
			"initialCode": "",
			"solution": "Hello World",
			"previewContainer": "preview-area",
			"validations": [
				{
					"type": "contains",
					"value": "Hello World",
					"message": "Schreibe <code>Hello World</code>"
				}
			]
		}
	]
}
